odoo/addons/account_reconcile_oca_queue/README.rst
odoo/addons/account_reconcile_oca_queue/__init__.py
odoo/addons/account_reconcile_oca_queue/__manifest__.py
odoo/addons/account_reconcile_oca_queue/i18n/account_reconcile_oca_queue.pot
odoo/addons/account_reconcile_oca_queue/i18n/it.po
odoo/addons/account_reconcile_oca_queue/models/__init__.py
odoo/addons/account_reconcile_oca_queue/models/account_bank_statement_line.py
odoo/addons/account_reconcile_oca_queue/models/res_company.py
odoo/addons/account_reconcile_oca_queue/models/res_config_settings.py
odoo/addons/account_reconcile_oca_queue/readme/CONTRIBUTORS.md
odoo/addons/account_reconcile_oca_queue/readme/DESCRIPTION.md
odoo/addons/account_reconcile_oca_queue/static/description/icon.png
odoo/addons/account_reconcile_oca_queue/static/description/index.html
odoo/addons/account_reconcile_oca_queue/tests/__init__.py
odoo/addons/account_reconcile_oca_queue/tests/test_bank_account_reconcile.py
odoo/addons/account_reconcile_oca_queue/views/res_config_settings.xml
odoo_addon_account_reconcile_oca_queue-18.0.1.1.0.2.dist-info/METADATA
odoo_addon_account_reconcile_oca_queue-18.0.1.1.0.2.dist-info/WHEEL
odoo_addon_account_reconcile_oca_queue-18.0.1.1.0.2.dist-info/top_level.txt
odoo_addon_account_reconcile_oca_queue-18.0.1.1.0.2.dist-info/RECORD
