Metadata-Version: 2.1
Name: odoo-addon-account_reconcile_oca_queue
Version: 18.0.1.1.0.2
Requires-Python: >=3.10
Requires-Dist: odoo-addon-account_reconcile_oca==18.0.*
Requires-Dist: odoo-addon-queue_job==18.0.*
Requires-Dist: odoo==18.0.*
Summary: Auto-reconcile in queue jobs
Home-page: https://github.com/OCA/account-reconcile
License: AGPL-3
Author: BCIM,Odoo Community Association (OCA)
Author-email: support@odoo-community.org
Classifier: Programming Language :: Python
Classifier: Framework :: Odoo
Classifier: Framework :: Odoo :: 18.0
Classifier: License :: OSI Approved :: GNU Affero General Public License v3
